Fddns.py
Fddns-1.0.0.dist-info/LICENSE
Fddns-1.0.0.dist-info/METADATA
Fddns-1.0.0.dist-info/WHEEL
Fddns-1.0.0.dist-info/top_level.txt
Fddns-1.0.0.dist-info/RECORD
