Metadata-Version: 2.1
Name: Fddns
Version: 1.0.0
Summary: DDNS with aliyun SDK
Author-email: GeorgeWu <wuzhaoqi1015@163.com>
License: Copyright (c) 2018 The Python Packaging Authority        
Classifier: Programming Language :: Python :: 3
Classifier: License :: OSI Approved :: MIT License
Classifier: Operating System :: OS Independent
Requires-Python: >=3.6
License-File: LICENSE
